htmx_rest/__init__.py
htmx_rest/apps.py
htmx_rest/negotiator.py
htmx_rest/renderers.py
htmx_rest/settings.py
htmx_rest/util.py
htmx_rest/tests/__init__.py
htmx_rest/tests/settings.py
htmx_rest/tests/test_negotiator.py
htmx_rest/tests/test_renderers.py
htmx_rest/tests/test_util.py
django_htmx_rest-0.0.1b2.dist-info/LICENSE
django_htmx_rest-0.0.1b2.dist-info/METADATA
django_htmx_rest-0.0.1b2.dist-info/WHEEL
django_htmx_rest-0.0.1b2.dist-info/top_level.txt
django_htmx_rest-0.0.1b2.dist-info/RECORD
