Metadata-Version: 2.1
Name: django-htmx-rest
Version: 0.0.1b2
Summary: Bringing together django, django rest framework, and htmx
Home-page: https://github.com/jdevries3133/django_htmx_rest
Author: Jack DeVries
Author-email: jdevries3133@gmail.com
License: UNKNOWN
Project-URL: Bug Tracker, https://github.com/jdevries3133/django_htmx_rest/issues
Platform: UNKNOWN
Classifier: Programming Language :: Python :: 3
Classifier: License :: OSI Approved :: MIT License
Classifier: Operating System :: OS Independent
Requires-Python: >=3.6
License-File: LICENSE
Requires-Dist: django (>=2.2)
Requires-Dist: djangorestframework (>=3.8)
